ProteinStructureVisualizer/__init__.py
ProteinStructureVisualizer/main.py
ProteinStructureVisualizer-1.0.6.dist-info/LICENSE
ProteinStructureVisualizer-1.0.6.dist-info/METADATA
ProteinStructureVisualizer-1.0.6.dist-info/WHEEL
ProteinStructureVisualizer-1.0.6.dist-info/entry_points.txt
ProteinStructureVisualizer-1.0.6.dist-info/top_level.txt
ProteinStructureVisualizer-1.0.6.dist-info/RECORD
