Metadata-Version: 2.1
Name: ProteinStructureVisualizer
Version: 1.0.6
Summary: A tool for 3D visualization of monomeric protein structures from PDB files
Author-email: Susan Ling <srling@uw.edu>
License: MIT
Project-URL: homepage, https://github.com/srling1125/ProteinStructureVisualizer
Keywords: protein,structure,visualization,bioinformatics
Classifier: Intended Audience :: Science/Research
Classifier: License :: OSI Approved :: MIT License
Classifier: Programming Language :: Python :: 3
Classifier: Topic :: Scientific/Engineering :: Bio-Informatics
Requires-Python: >=3.7
License-File: LICENSE
Requires-Dist: pandas
Requires-Dist: plotly
Requires-Dist: networkx
Requires-Dist: biopandas
Requires-Dist: prody
Requires-Dist: graphein
Provides-Extra: dev
Requires-Dist: pytest; extra == "dev"
Requires-Dist: black; extra == "dev"
Requires-Dist: flake8; extra == "dev"
